microcdt.py
microcdt-0.1.1.dist-info/DESCRIPTION.rst
microcdt-0.1.1.dist-info/METADATA
microcdt-0.1.1.dist-info/RECORD
microcdt-0.1.1.dist-info/WHEEL
microcdt-0.1.1.dist-info/metadata.json
microcdt-0.1.1.dist-info/top_level.txt
