Metadata-Version: 2.0
Name: microcdt
Version: 0.1.1
Summary: A microscopic client library for accessing Cloudant databases
Home-page: https://github.com/xpqz/microcdt
Author: Stefan Kruger
Author-email: stefan.kruger@gmail.com
License: UNKNOWN
Keywords: databases development
Platform: UNKNOWN
Classifier: Development Status :: 4 - Beta
Classifier: Intended Audience :: Developers
Classifier: Topic :: Software Development :: Build Tools
Classifier: License :: OSI Approved :: Apache Software License
Classifier: Programming Language :: Python :: 2
Classifier: Programming Language :: Python :: 2.7
Classifier: Programming Language :: Python :: 3
Requires-Dist: requests
